MANIFEST.in
README.md
setup.py
epub_conversion/__init__.py
epub_conversion/converter.py
epub_conversion/utils.py
epub_conversion/wiki_decoder.py
epub_conversion.egg-info/PKG-INFO
epub_conversion.egg-info/SOURCES.txt
epub_conversion.egg-info/dependency_links.txt
epub_conversion.egg-info/not-zip-safe
epub_conversion.egg-info/requires.txt
epub_conversion.egg-info/top_level.txt