Metadata-Version: 1.1
Name: epub-conversion
Version: 1.0.1
Summary: Python package for converting xml and epubs to text files
Home-page: https://github.com/JonathanRaiman/epub_conversion
Author: Jonathan Raiman
Author-email: jraiman at mit dot edu
License: MIT
Download-URL: https://github.com/JonathanRaiman/epub_conversion
Keywords: XML,epub,tokenization,NLP
Platform: any
Classifier: Intended Audience :: Science/Research
Classifier: Operating System :: OS Independent
Classifier: Programming Language :: Python :: 3.3
Classifier: Topic :: Text Processing :: Linguistic
